ppd/__init__.py
ppd/__main__.py
ppd-0.2.2.dist-info/LICENSE
ppd-0.2.2.dist-info/METADATA
ppd-0.2.2.dist-info/WHEEL
ppd-0.2.2.dist-info/entry_points.txt
ppd-0.2.2.dist-info/top_level.txt
ppd-0.2.2.dist-info/RECORD
