Metadata-Version: 2.1
Name: ppd
Version: 0.2.2
Summary: Download 'periodic' Jehovah's Witnesses publications from the command line
Home-page: https://github.com/mikiTesf/ppd
Author: Mikyas Tesfamichael
Author-email: mickyastesfamichael@gmail.com
License: UNKNOWN
Platform: UNKNOWN
Classifier: Programming Language :: Python :: 3.6
Classifier: License :: OSI Approved :: MIT License
Classifier: Operating System :: OS Independent
Requires-Python: >=3.6
Requires-Dist: requests
Requires-Dist: wget
